setup.py
distributions_tb/Binomialdistribution.py
distributions_tb/Gaussiandistribution.py
distributions_tb/Generaldistribution.py
distributions_tb/__init__.py
distributions_tb.egg-info/PKG-INFO
distributions_tb.egg-info/SOURCES.txt
distributions_tb.egg-info/dependency_links.txt
distributions_tb.egg-info/not-zip-safe
distributions_tb.egg-info/top_level.txt