Metadata-Version: 1.0
Name: distributions-tb
Version: 0.1
Summary: Different distributions
Home-page: UNKNOWN
Author: Thomas Breuer
Author-email: UNKNOWN
License: UNKNOWN
Platform: UNKNOWN
